chat_limiter/__init__.py
chat_limiter/adapters.py
chat_limiter/batch.py
chat_limiter/limiter.py
chat_limiter/models.py
chat_limiter/providers.py
chat_limiter/types.py
chat_limiter/utils.py
chat_limiter-0.16.0.dist-info/METADATA
chat_limiter-0.16.0.dist-info/WHEEL
chat_limiter-0.16.0.dist-info/licenses/LICENSE
chat_limiter-0.16.0.dist-info/RECORD
