Metadata-Version: 2.4
Name: chat-limiter
Version: 0.16.0
Summary: A Pythonic rate limiter for OpenAI, Anthropic, and OpenRouter APIs
Author-email: Ivan Arcuschin <ivan@arcuschin.com>
License-File: LICENSE
Keywords: anthropic,api,openai,openrouter,rate-limiting
Classifier: Development Status :: 3 - Alpha
Classifier: Intended Audience :: Developers
Classifier: License :: OSI Approved :: MIT License
Classifier: Programming Language :: Python :: 3
Classifier: Programming Language :: Python :: 3.10
Classifier: Programming Language :: Python :: 3.11
Classifier: Programming Language :: Python :: 3.12
Classifier: Topic :: Software Development :: Libraries :: Python Modules
Requires-Python: >=3.10
Requires-Dist: build>=1.2.2.post1
Requires-Dist: httpx>=0.27.0
Requires-Dist: pydantic>=2.0.0
Requires-Dist: pyrate-limiter>=3.5.0
Requires-Dist: tenacity>=8.0.0
Requires-Dist: tqdm>=4.60.0
Requires-Dist: twine>=6.1.0
Requires-Dist: typing-extensions>=4.8.0
